api_client/__init__.py
api_client/api_client.py
api_client/api_formatter.py
api_client/api_thread_pool.py
api_client/connection_pool_cache.py
api_client/constants.py
api_client/exceptions.py
api_client/utility.py
api_client/config/logging.json
api_client/formatter/__init__.py
api_client/formatter/util.py
concurrent_api_client-0.0.1.dist-info/METADATA
concurrent_api_client-0.0.1.dist-info/WHEEL
concurrent_api_client-0.0.1.dist-info/top_level.txt
concurrent_api_client-0.0.1.dist-info/RECORD
