Metadata-Version: 2.1
Name: concurrent-api-client
Version: 0.0.1
Summary: An example for API client using python request library
Home-page: https://github.com/tatoflam/concurrent-api-client
Author: tatoflam
Author-email: tatoflam@gamil.com
License: MIT
Project-URL: Issue Tracker, https://github.com/tatoflam/concurrent-api-client/issues
Keywords: request,API,REST,client,async,concurrent
Platform: UNKNOWN
Classifier: Development Status :: 4 - Beta
Classifier: Intended Audience :: Developers
Classifier: License :: OSI Approved :: MIT License
Classifier: Operating System :: MacOS :: MacOS X
Classifier: Programming Language :: Python :: 3
Classifier: Topic :: Utilities
Classifier: Topic :: Software Development :: Libraries :: Python Modules
Requires-Python: >=3.7
Requires-Dist: attrs (==21.2.0)
Requires-Dist: certifi (==2021.10.8)
Requires-Dist: charset-normalizer (==2.0.7)
Requires-Dist: idna (==3.3)
Requires-Dist: importlib-metadata (==4.8.1)
Requires-Dist: iniconfig (==1.1.1)
Requires-Dist: packaging (==21.0)
Requires-Dist: pluggy (==1.0.0)
Requires-Dist: py (==1.10.0)
Requires-Dist: pyparsing (==3.0.1)
Requires-Dist: pytest (==6.2.5)
Requires-Dist: pytest-runner (==5.3.1)
Requires-Dist: requests (==2.26.0)
Requires-Dist: requests-toolbelt (==0.9.1)
Requires-Dist: toml (==0.10.2)
Requires-Dist: typing-extensions (==3.10.0.2)
Requires-Dist: urllib3 (==1.26.7)
Requires-Dist: zipp (==3.6.0)
